grandpa/__init__.py
grandpa/built_in_nodes.py
grandpa/dict_keys.py
grandpa/graph_runtime.py
grandpa/multiprocessing_manager.py
grandpa/node.py
grandpa/routing.py
grandpa/template_parser.py
grandpa/utils/__init__.py
grandpa/utils/__utf_char_map__.py
grandpa/utils/bounding_box.py
grandpa/utils/datamanager.py
grandpa/utils/gaussian.py
grandpa/utils/gaussian_generator.py
grandpa/utils/generator.py
grandpa/utils/mapping_dicts.py
grandpa/utils/math.py
grandpa/utils/process.py
grandpa/utils/standard.py
grandpa-0.6.3.dist-info/LICENSE
grandpa-0.6.3.dist-info/METADATA
grandpa-0.6.3.dist-info/WHEEL
grandpa-0.6.3.dist-info/top_level.txt
grandpa-0.6.3.dist-info/RECORD
