Metadata-Version: 2.1
Name: grandpa
Version: 0.6.3
Home-page: https://dev.azure.com/matthiasrieger/ImageRecognition/_git/ir-graml-core
Author: Bizerba AI Team
Author-email: pascal.iwohn@bizerba.com
License: MIT License
License-File: LICENSE
Requires-Dist: setuptools
Requires-Dist: wheel
Requires-Dist: imageio
Requires-Dist: numpy
Requires-Dist: opencv-python
Requires-Dist: Pillow
Requires-Dist: psutil
Requires-Dist: tqdm
